icmp_remote_shell/__init__.py
icmp_remote_shell/client.py
icmp_remote_shell/common.py
icmp_remote_shell/server.py
icmp_remote_shell-1.0.dist-info/METADATA
icmp_remote_shell-1.0.dist-info/RECORD
icmp_remote_shell-1.0.dist-info/WHEEL
icmp_remote_shell-1.0.dist-info/entry_points.txt
icmp_remote_shell-1.0.dist-info/top_level.txt
