Metadata-Version: 2.1
Name: icmp-remote-shell
Version: 1.0
Summary: Prototype of steganography remote shell using ICMP protocol for data hiding
Home-page: https://gitlab.com/alex-kostirin/icmp-remote-shell
Author: Alexey Kostyrin
Author-email: alex.kostirin@ya.ru
License: UNKNOWN
Platform: UNKNOWN
Classifier: Programming Language :: Python :: 3
Classifier: License :: OSI Approved :: MIT License
Classifier: Operating System :: OS Independent
